ShenruXuexiWebAnquanWannianSizhai/README.md
ShenruXuexiWebAnquanWannianSizhai/__init__.py
ShenruXuexiWebAnquanWannianSizhai/__main__.py
ShenruXuexiWebAnquanWannianSizhai/file.epub
ShenruXuexiWebAnquanWannianSizhai/index.html
ShenruXuexiWebAnquanWannianSizhai/css/__init__.py
ShenruXuexiWebAnquanWannianSizhai/css/annotations.css
ShenruXuexiWebAnquanWannianSizhai/css/main.css
ShenruXuexiWebAnquanWannianSizhai/css/normalize.css
ShenruXuexiWebAnquanWannianSizhai/css/popup.css
ShenruXuexiWebAnquanWannianSizhai/font/__init__.py
ShenruXuexiWebAnquanWannianSizhai/font/fontello.eot
ShenruXuexiWebAnquanWannianSizhai/font/fontello.svg
ShenruXuexiWebAnquanWannianSizhai/font/fontello.ttf
ShenruXuexiWebAnquanWannianSizhai/font/fontello.woff
ShenruXuexiWebAnquanWannianSizhai/img/__init__.py
ShenruXuexiWebAnquanWannianSizhai/img/annotator-glyph-sprite.png
ShenruXuexiWebAnquanWannianSizhai/img/annotator-icon-sprite.png
ShenruXuexiWebAnquanWannianSizhai/img/apple-touch-icon.png
ShenruXuexiWebAnquanWannianSizhai/img/cancelfullscreen.png
ShenruXuexiWebAnquanWannianSizhai/img/close.png
ShenruXuexiWebAnquanWannianSizhai/img/fullscreen.png
ShenruXuexiWebAnquanWannianSizhai/img/loader.gif
ShenruXuexiWebAnquanWannianSizhai/img/menu-icon.png
ShenruXuexiWebAnquanWannianSizhai/img/save.png
ShenruXuexiWebAnquanWannianSizhai/img/saved.png
ShenruXuexiWebAnquanWannianSizhai/img/settings-s.png
ShenruXuexiWebAnquanWannianSizhai/img/settings.png
ShenruXuexiWebAnquanWannianSizhai/img/star.png
ShenruXuexiWebAnquanWannianSizhai/js/__init__.py
ShenruXuexiWebAnquanWannianSizhai/js/epub.js
ShenruXuexiWebAnquanWannianSizhai/js/epub.min.js
ShenruXuexiWebAnquanWannianSizhai/js/epub.min.map
ShenruXuexiWebAnquanWannianSizhai/js/hooks.min.js
ShenruXuexiWebAnquanWannianSizhai/js/hooks.min.map
ShenruXuexiWebAnquanWannianSizhai/js/reader.js
ShenruXuexiWebAnquanWannianSizhai/js/reader.js.map
ShenruXuexiWebAnquanWannianSizhai/js/reader.min.js
ShenruXuexiWebAnquanWannianSizhai/js/reader.min.map
shenru_xuexi_web_anquan_wannian_sizhai-2024.3.2.0.dist-info/METADATA
shenru_xuexi_web_anquan_wannian_sizhai-2024.3.2.0.dist-info/WHEEL
shenru_xuexi_web_anquan_wannian_sizhai-2024.3.2.0.dist-info/entry_points.txt
shenru_xuexi_web_anquan_wannian_sizhai-2024.3.2.0.dist-info/top_level.txt
shenru_xuexi_web_anquan_wannian_sizhai-2024.3.2.0.dist-info/RECORD
